openfisca_core/__init__.py
openfisca_core/formula_helpers.py
openfisca_core/memory_config.py
openfisca_core/model_api.py
openfisca_core/rates.py
openfisca_core/simulation_builder.py
openfisca_core/types.py
openfisca_core/commons/__init__.py
openfisca_core/commons/dummy.py
openfisca_core/commons/formulas.py
openfisca_core/commons/misc.py
openfisca_core/commons/py.typed
openfisca_core/commons/rates.py
openfisca_core/commons/tests/__init__.py
openfisca_core/commons/tests/test_dummy.py
openfisca_core/commons/tests/test_formulas.py
openfisca_core/commons/tests/test_rates.py
openfisca_core/data_storage/__init__.py
openfisca_core/data_storage/in_memory_storage.py
openfisca_core/data_storage/on_disk_storage.py
openfisca_core/data_storage/types.py
openfisca_core/entities/__init__.py
openfisca_core/entities/_core_entity.py
openfisca_core/entities/_description.py
openfisca_core/entities/entity.py
openfisca_core/entities/group_entity.py
openfisca_core/entities/helpers.py
openfisca_core/entities/py.typed
openfisca_core/entities/role.py
openfisca_core/entities/types.py
openfisca_core/entities/tests/__init__.py
openfisca_core/entities/tests/test_entity.py
openfisca_core/entities/tests/test_group_entity.py
openfisca_core/entities/tests/test_role.py
openfisca_core/errors/__init__.py
openfisca_core/errors/cycle_error.py
openfisca_core/errors/empty_argument_error.py
openfisca_core/errors/nan_creation_error.py
openfisca_core/errors/parameter_not_found_error.py
openfisca_core/errors/parameter_parsing_error.py
openfisca_core/errors/period_mismatch_error.py
openfisca_core/errors/situation_parsing_error.py
openfisca_core/errors/spiral_error.py
openfisca_core/errors/variable_name_config_error.py
openfisca_core/errors/variable_not_found_error.py
openfisca_core/experimental/__init__.py
openfisca_core/experimental/_errors.py
openfisca_core/experimental/_memory_config.py
openfisca_core/holders/__init__.py
openfisca_core/holders/helpers.py
openfisca_core/holders/holder.py
openfisca_core-44.2.1.dist-info/licenses/LICENSE
openfisca_core-44.2.1.dist-info/METADATA
openfisca_core-44.2.1.dist-info/WHEEL
openfisca_core-44.2.1.dist-info/entry_points.txt
openfisca_core-44.2.1.dist-info/top_level.txt
openfisca_core-44.2.1.dist-info/RECORD
