Metadata-Version: 2.4
Name: OpenFisca-Core
Version: 44.2.1
Summary: A versatile microsimulation free software
Home-page: https://github.com/openfisca/openfisca-core
Author: OpenFisca Team
Author-email: contact@openfisca.org
License: License-Expression :: AGPL-3.0-or-later
Keywords: benefit microsimulation social tax
Classifier: Development Status :: 5 - Production/Stable
Classifier: Operating System :: POSIX
Classifier: Programming Language :: Python
Classifier: Programming Language :: Python :: 3.10
Classifier: Programming Language :: Python :: 3.11
Classifier: Programming Language :: Python :: 3.12
Classifier: Programming Language :: Python :: 3.13
Classifier: Topic :: Scientific/Engineering :: Information Analysis
License-File: LICENSE
Requires-Dist: PyYAML<7.0,>=6.0
Requires-Dist: StrEnum<0.5.0,>=0.4.8
Requires-Dist: dpath<3.0,>=2.2.0
Requires-Dist: numexpr<3.0,>=2.10.1
Requires-Dist: numpy<2.0,>=1.24.2; python_version < "3.11"
Requires-Dist: numpy<=3,>=1.26.0; python_version <= "3.12"
Requires-Dist: numpy<=3,>=2.1.0; python_version >= "3.13"
Requires-Dist: pendulum<4.0.0,>=3.0.0
Requires-Dist: psutil<6.0,>=5.9.4
Requires-Dist: pytest<9.0,>=8.3.3
Requires-Dist: sortedcontainers<3.0,>=2.4.0
Requires-Dist: typing_extensions<5.0,>=4.5.0
Provides-Extra: web-api
Requires-Dist: Flask<4.0,>=2.2.3; extra == "web-api"
Requires-Dist: Flask-Cors<4.0,>=3.0.10; extra == "web-api"
Requires-Dist: gunicorn<22.0,>=21.0; extra == "web-api"
Requires-Dist: Werkzeug<4.0,>=2.2.3; extra == "web-api"
Provides-Extra: dev
Requires-Dist: black<25.0,>=24.8.0; extra == "dev"
Requires-Dist: codespell<3.0,>=2.3.0; extra == "dev"
Requires-Dist: colorama<0.5,>=0.4.4; extra == "dev"
Requires-Dist: darglint<2.0,>=1.8.1; extra == "dev"
Requires-Dist: flake8<8.0.0,>=7.1.1; extra == "dev"
Requires-Dist: flake8-bugbear<25.0,>=24.8.19; extra == "dev"
Requires-Dist: flake8-docstrings<2.0,>=1.7.0; extra == "dev"
Requires-Dist: flake8-print<6.0,>=5.0.0; extra == "dev"
Requires-Dist: flake8-rst-docstrings<0.4.0,>=0.3.0; extra == "dev"
Requires-Dist: idna<4.0,>=3.10; extra == "dev"
Requires-Dist: isort<6.0,>=5.13.2; extra == "dev"
Requires-Dist: mypy<2.0,>=1.11.2; extra == "dev"
Requires-Dist: openapi-spec-validator<0.8.0,>=0.7.1; extra == "dev"
Requires-Dist: pylint<4.0,>=3.3.1; extra == "dev"
Requires-Dist: pylint-per-file-ignores<2.0,>=1.3.2; extra == "dev"
Requires-Dist: pyright<2.0,>=1.1.382; extra == "dev"
Requires-Dist: ruff<1.0,>=0.6.9; extra == "dev"
Requires-Dist: ruff-lsp<1.0,>=0.0.57; extra == "dev"
Requires-Dist: Flask<4.0,>=2.2.3; extra == "dev"
Requires-Dist: Flask-Cors<4.0,>=3.0.10; extra == "dev"
Requires-Dist: gunicorn<22.0,>=21.0; extra == "dev"
Requires-Dist: Werkzeug<4.0,>=2.2.3; extra == "dev"
Requires-Dist: openpyxl<4.0,>=3.1.2; extra == "dev"
Provides-Extra: ci
Requires-Dist: build<0.11.0,>=0.10.0; extra == "ci"
Requires-Dist: twine<7.0,>=6.0; extra == "ci"
Requires-Dist: wheel<0.41.0,>=0.40.0; extra == "ci"
Provides-Extra: tracker
Requires-Dist: OpenFisca-Tracker<0.5.0,>=0.4.0; extra == "tracker"
Provides-Extra: excel
Requires-Dist: openpyxl<4.0,>=3.1.2; extra == "excel"
Dynamic: author
Dynamic: author-email
Dynamic: classifier
Dynamic: description
Dynamic: description-content-type
Dynamic: home-page
Dynamic: keywords
Dynamic: license
Dynamic: license-file
Dynamic: provides-extra
Dynamic: requires-dist
Dynamic: summary
